{
  "schema_version": 1,
  "commodity": {
    "id": "cadmium",
    "title": "Cadmium",
    "update_year": 2022,
    "source_url": "https://www.usgs.gov/media/files/cadmium-historical-statistics-data-series-140",
    "download_url": "https://d9-wret.s3.us-west-2.amazonaws.com/assets/palladium/production/s3fs-public/media/files/ds140-cadmium-2022.xlsx",
    "catalog_url": "https://www.usgs.gov/centers/national-minerals-information-center/historical-statistics-mineral-commodities-united",
    "access_date": "2026-07-10",
    "historical_scope": {
      "start": 1861,
      "end": 1992
    },
    "transcription_status": "machine-extracted-xlsx",
    "conversion_methodology": "No project conversion. Numeric values are reproduced from USGS-standardized workbook cells.",
    "caveat": "Blank, unavailable, withheld, and other nonnumeric cells are counted separately and are never treated as zero."
  },
  "summary": {
    "series_count": 1,
    "measure_count": 9,
    "observation_count": 719,
    "year_start": 1900,
    "year_end": 1992
  },
  "series": [
    {
      "id": "cadmium",
      "label": "Cadmium",
      "worksheet": "Cadmium",
      "header_row": 5,
      "source_unit": "metric tons (t) cadmium content",
      "year_start": 1900,
      "year_end": 1992,
      "measures": [
        {
          "id": "production",
          "label": "Production",
          "column": 2,
          "unit": "metric tons (t) cadmium content",
          "price_basis": "not-price",
          "observation_count": 93,
          "year_start": 1900,
          "year_end": 1992,
          "missing": {
            "blank": 0,
            "not_available": 0,
            "withheld": 0,
            "other_nonnumeric": 0
          },
          "observations": [
            [
              1900,
              0,
              6
            ],
            [
              1901,
              0,
              7
            ],
            [
              1902,
              0,
              8
            ],
            [
              1903,
              0,
              9
            ],
            [
              1904,
              0,
              10
            ],
            [
              1905,
              0,
              11
            ],
            [
              1906,
              0.136,
              12
            ],
            [
              1907,
              6.35,
              13
            ],
            [
              1908,
              3.63,
              14
            ],
            [
              1909,
              2.41,
              15
            ],
            [
              1910,
              2.13,
              16
            ],
            [
              1911,
              11.9,
              17
            ],
            [
              1912,
              23.8,
              18
            ],
            [
              1913,
              24.6,
              19
            ],
            [
              1914,
              41.5,
              20
            ],
            [
              1915,
              41.5,
              21
            ],
            [
              1916,
              61.4,
              22
            ],
            [
              1917,
              94.1,
              23
            ],
            [
              1918,
              57.7,
              24
            ],
            [
              1919,
              45.3,
              25
            ],
            [
              1920,
              58.7,
              26
            ],
            [
              1921,
              31.1,
              27
            ],
            [
              1922,
              59.7,
              28
            ],
            [
              1923,
              83.4,
              29
            ],
            [
              1924,
              58.7,
              30
            ],
            [
              1925,
              228,
              31
            ],
            [
              1926,
              368,
              32
            ],
            [
              1927,
              488,
              33
            ],
            [
              1928,
              851,
              34
            ],
            [
              1929,
              1130,
              35
            ],
            [
              1930,
              1260,
              36
            ],
            [
              1931,
              477,
              37
            ],
            [
              1932,
              363,
              38
            ],
            [
              1933,
              1030,
              39
            ],
            [
              1934,
              1260,
              40
            ],
            [
              1935,
              1580,
              41
            ],
            [
              1936,
              1650,
              42
            ],
            [
              1937,
              1940,
              43
            ],
            [
              1938,
              1950,
              44
            ],
            [
              1939,
              2170,
              45
            ],
            [
              1940,
              2890,
              46
            ],
            [
              1941,
              3280,
              47
            ],
            [
              1942,
              3340,
              48
            ],
            [
              1943,
              3840,
              49
            ],
            [
              1944,
              3980,
              50
            ],
            [
              1945,
              3800,
              51
            ],
            [
              1946,
              2940,
              52
            ],
            [
              1947,
              3860,
              53
            ],
            [
              1948,
              3530,
              54
            ],
            [
              1949,
              3730,
              55
            ],
            [
              1950,
              4170,
              56
            ],
            [
              1951,
              3770,
              57
            ],
            [
              1952,
              3890,
              58
            ],
            [
              1953,
              4430,
              59
            ],
            [
              1954,
              4330,
              60
            ],
            [
              1955,
              4420,
              61
            ],
            [
              1956,
              4810,
              62
            ],
            [
              1957,
              4790,
              63
            ],
            [
              1958,
              4390,
              64
            ],
            [
              1959,
              3900,
              65
            ],
            [
              1960,
              4740,
              66
            ],
            [
              1961,
              4750,
              67
            ],
            [
              1962,
              5050,
              68
            ],
            [
              1963,
              4530,
              69
            ],
            [
              1964,
              4740,
              70
            ],
            [
              1965,
              4390,
              71
            ],
            [
              1966,
              4750,
              72
            ],
            [
              1967,
              3950,
              73
            ],
            [
              1968,
              4830,
              74
            ],
            [
              1969,
              5740,
              75
            ],
            [
              1970,
              4290,
              76
            ],
            [
              1971,
              3600,
              77
            ],
            [
              1972,
              3760,
              78
            ],
            [
              1973,
              3400,
              79
            ],
            [
              1974,
              3020,
              80
            ],
            [
              1975,
              1990,
              81
            ],
            [
              1976,
              2050,
              82
            ],
            [
              1977,
              2000,
              83
            ],
            [
              1978,
              1650,
              84
            ],
            [
              1979,
              1820,
              85
            ],
            [
              1980,
              1580,
              86
            ],
            [
              1981,
              1600,
              87
            ],
            [
              1982,
              1010,
              88
            ],
            [
              1983,
              1050,
              89
            ],
            [
              1984,
              1690,
              90
            ],
            [
              1985,
              1600,
              91
            ],
            [
              1986,
              1490,
              92
            ],
            [
              1987,
              1520,
              93
            ],
            [
              1988,
              1890,
              94
            ],
            [
              1989,
              1550,
              95
            ],
            [
              1990,
              1680,
              96
            ],
            [
              1991,
              1680,
              97
            ],
            [
              1992,
              1620,
              98
            ]
          ]
        },
        {
          "id": "imports",
          "label": "Imports",
          "column": 3,
          "unit": "metric tons (t) cadmium content",
          "price_basis": "not-price",
          "observation_count": 83,
          "year_start": 1903,
          "year_end": 1992,
          "missing": {
            "blank": 0,
            "not_available": 10,
            "withheld": 0,
            "other_nonnumeric": 0
          },
          "observations": [
            [
              1903,
              3.94,
              9
            ],
            [
              1904,
              3.47,
              10
            ],
            [
              1905,
              3.69,
              11
            ],
            [
              1906,
              6.27,
              12
            ],
            [
              1907,
              0.886,
              13
            ],
            [
              1908,
              1.62,
              14
            ],
            [
              1909,
              4.02,
              15
            ],
            [
              1910,
              1.84,
              16
            ],
            [
              1911,
              2.44,
              17
            ],
            [
              1912,
              2.38,
              18
            ],
            [
              1913,
              0.751,
              19
            ],
            [
              1914,
              0.2,
              20
            ],
            [
              1915,
              0.122,
              21
            ],
            [
              1921,
              0.046,
              27
            ],
            [
              1922,
              1.02,
              28
            ],
            [
              1923,
              0.007,
              29
            ],
            [
              1924,
              0.501,
              30
            ],
            [
              1925,
              0.002,
              31
            ],
            [
              1927,
              10.2,
              33
            ],
            [
              1928,
              106,
              34
            ],
            [
              1929,
              97.2,
              35
            ],
            [
              1930,
              18.2,
              36
            ],
            [
              1931,
              0.123,
              37
            ],
            [
              1933,
              49.4,
              39
            ],
            [
              1934,
              57.1,
              40
            ],
            [
              1935,
              84.1,
              41
            ],
            [
              1936,
              261,
              42
            ],
            [
              1937,
              376,
              43
            ],
            [
              1938,
              10.2,
              44
            ],
            [
              1939,
              141,
              45
            ],
            [
              1940,
              12.5,
              46
            ],
            [
              1941,
              66.9,
              47
            ],
            [
              1942,
              24.2,
              48
            ],
            [
              1943,
              22.2,
              49
            ],
            [
              1944,
              30.2,
              50
            ],
            [
              1945,
              13,
              51
            ],
            [
              1946,
              7.9,
              52
            ],
            [
              1947,
              9.21,
              53
            ],
            [
              1948,
              4.45,
              54
            ],
            [
              1949,
              71.3,
              55
            ],
            [
              1950,
              286,
              56
            ],
            [
              1951,
              40.9,
              57
            ],
            [
              1952,
              675,
              58
            ],
            [
              1953,
              705,
              59
            ],
            [
              1954,
              182,
              60
            ],
            [
              1955,
              421,
              61
            ],
            [
              1956,
              1410,
              62
            ],
            [
              1957,
              719,
              63
            ],
            [
              1958,
              455,
              64
            ],
            [
              1959,
              743,
              65
            ],
            [
              1960,
              427,
              66
            ],
            [
              1961,
              489,
              67
            ],
            [
              1962,
              507,
              68
            ],
            [
              1963,
              450,
              69
            ],
            [
              1964,
              501,
              70
            ],
            [
              1965,
              962,
              71
            ],
            [
              1966,
              1520,
              72
            ],
            [
              1967,
              720,
              73
            ],
            [
              1968,
              874,
              74
            ],
            [
              1969,
              489,
              75
            ],
            [
              1970,
              1130,
              76
            ],
            [
              1971,
              1590,
              77
            ],
            [
              1972,
              1100,
              78
            ],
            [
              1973,
              1770,
              79
            ],
            [
              1974,
              1800,
              80
            ],
            [
              1975,
              2380,
              81
            ],
            [
              1976,
              3330,
              82
            ],
            [
              1977,
              2330,
              83
            ],
            [
              1978,
              2880,
              84
            ],
            [
              1979,
              2570,
              85
            ],
            [
              1980,
              2620,
              86
            ],
            [
              1981,
              3090,
              87
            ],
            [
              1982,
              2310,
              88
            ],
            [
              1983,
              2200,
              89
            ],
            [
              1984,
              1890,
              90
            ],
            [
              1985,
              1990,
              91
            ],
            [
              1986,
              3170,
              92
            ],
            [
              1987,
              2700,
              93
            ],
            [
              1988,
              2480,
              94
            ],
            [
              1989,
              2790,
              95
            ],
            [
              1990,
              1740,
              96
            ],
            [
              1991,
              2040,
              97
            ],
            [
              1992,
              1960,
              98
            ]
          ]
        },
        {
          "id": "exports",
          "label": "Exports",
          "column": 4,
          "unit": "metric tons (t) cadmium content",
          "price_basis": "not-price",
          "observation_count": 57,
          "year_start": 1912,
          "year_end": 1992,
          "missing": {
            "blank": 0,
            "not_available": 36,
            "withheld": 0,
            "other_nonnumeric": 0
          },
          "observations": [
            [
              1912,
              18,
              18
            ],
            [
              1918,
              18,
              24
            ],
            [
              1937,
              11,
              43
            ],
            [
              1938,
              208,
              44
            ],
            [
              1940,
              176,
              46
            ],
            [
              1941,
              78,
              47
            ],
            [
              1942,
              114,
              48
            ],
            [
              1943,
              71,
              49
            ],
            [
              1944,
              249,
              50
            ],
            [
              1945,
              46,
              51
            ],
            [
              1946,
              64,
              52
            ],
            [
              1947,
              138,
              53
            ],
            [
              1948,
              434,
              54
            ],
            [
              1949,
              257,
              55
            ],
            [
              1950,
              160,
              56
            ],
            [
              1951,
              275,
              57
            ],
            [
              1952,
              136,
              58
            ],
            [
              1953,
              30,
              59
            ],
            [
              1954,
              453,
              60
            ],
            [
              1955,
              632,
              61
            ],
            [
              1956,
              583,
              62
            ],
            [
              1957,
              314,
              63
            ],
            [
              1958,
              263,
              64
            ],
            [
              1959,
              408,
              65
            ],
            [
              1960,
              1110,
              66
            ],
            [
              1961,
              318,
              67
            ],
            [
              1962,
              325,
              68
            ],
            [
              1963,
              596,
              69
            ],
            [
              1964,
              653,
              70
            ],
            [
              1965,
              33,
              71
            ],
            [
              1966,
              172,
              72
            ],
            [
              1967,
              313,
              73
            ],
            [
              1968,
              240,
              74
            ],
            [
              1969,
              492,
              75
            ],
            [
              1970,
              169,
              76
            ],
            [
              1971,
              30,
              77
            ],
            [
              1972,
              462,
              78
            ],
            [
              1973,
              139,
              79
            ],
            [
              1974,
              28,
              80
            ],
            [
              1975,
              180,
              81
            ],
            [
              1976,
              229,
              82
            ],
            [
              1977,
              107,
              83
            ],
            [
              1978,
              326,
              84
            ],
            [
              1979,
              211,
              85
            ],
            [
              1980,
              236,
              86
            ],
            [
              1981,
              239,
              87
            ],
            [
              1982,
              11,
              88
            ],
            [
              1983,
              170,
              89
            ],
            [
              1984,
              106,
              90
            ],
            [
              1985,
              86,
              91
            ],
            [
              1986,
              38,
              92
            ],
            [
              1987,
              241,
              93
            ],
            [
              1988,
              613,
              94
            ],
            [
              1989,
              369,
              95
            ],
            [
              1990,
              385,
              96
            ],
            [
              1991,
              448,
              97
            ],
            [
              1992,
              213,
              98
            ]
          ]
        },
        {
          "id": "shipments",
          "label": "Shipments",
          "column": 5,
          "unit": "metric tons (t) cadmium content",
          "price_basis": "not-price",
          "observation_count": 64,
          "year_start": 1929,
          "year_end": 1992,
          "missing": {
            "blank": 0,
            "not_available": 29,
            "withheld": 0,
            "other_nonnumeric": 0
          },
          "observations": [
            [
              1929,
              1060,
              35
            ],
            [
              1930,
              755,
              36
            ],
            [
              1931,
              701,
              37
            ],
            [
              1932,
              524,
              38
            ],
            [
              1933,
              1110,
              39
            ],
            [
              1934,
              1120,
              40
            ],
            [
              1935,
              1830,
              41
            ],
            [
              1936,
              1650,
              42
            ],
            [
              1937,
              1840,
              43
            ],
            [
              1938,
              1150,
              44
            ],
            [
              1939,
              2350,
              45
            ],
            [
              1940,
              2930,
              46
            ],
            [
              1941,
              3200,
              47
            ],
            [
              1942,
              3280,
              48
            ],
            [
              1943,
              3780,
              49
            ],
            [
              1944,
              3880,
              50
            ],
            [
              1945,
              3600,
              51
            ],
            [
              1946,
              2800,
              52
            ],
            [
              1947,
              3560,
              53
            ],
            [
              1948,
              3470,
              54
            ],
            [
              1949,
              3570,
              55
            ],
            [
              1950,
              4020,
              56
            ],
            [
              1951,
              3520,
              57
            ],
            [
              1952,
              3510,
              58
            ],
            [
              1953,
              3690,
              59
            ],
            [
              1954,
              3590,
              60
            ],
            [
              1955,
              5070,
              61
            ],
            [
              1956,
              4960,
              62
            ],
            [
              1957,
              4580,
              63
            ],
            [
              1958,
              3590,
              64
            ],
            [
              1959,
              5110,
              65
            ],
            [
              1960,
              5440,
              66
            ],
            [
              1961,
              4640,
              67
            ],
            [
              1962,
              5470,
              68
            ],
            [
              1963,
              4590,
              69
            ],
            [
              1964,
              4400,
              70
            ],
            [
              1965,
              3690,
              71
            ],
            [
              1966,
              5350,
              72
            ],
            [
              1967,
              4360,
              73
            ],
            [
              1968,
              5100,
              74
            ],
            [
              1969,
              5890,
              75
            ],
            [
              1970,
              3110,
              76
            ],
            [
              1971,
              3530,
              77
            ],
            [
              1972,
              4750,
              78
            ],
            [
              1973,
              3910,
              79
            ],
            [
              1974,
              2950,
              80
            ],
            [
              1975,
              742,
              81
            ],
            [
              1976,
              2710,
              82
            ],
            [
              1977,
              1840,
              83
            ],
            [
              1978,
              1960,
              84
            ],
            [
              1979,
              2470,
              85
            ],
            [
              1980,
              1270,
              86
            ],
            [
              1981,
              1380,
              87
            ],
            [
              1982,
              1830,
              88
            ],
            [
              1983,
              1500,
              89
            ],
            [
              1984,
              1810,
              90
            ],
            [
              1985,
              1790,
              91
            ],
            [
              1986,
              2030,
              92
            ],
            [
              1987,
              1920,
              93
            ],
            [
              1988,
              2070,
              94
            ],
            [
              1989,
              2020,
              95
            ],
            [
              1990,
              1860,
              96
            ],
            [
              1991,
              1740,
              97
            ],
            [
              1992,
              2080,
              98
            ]
          ]
        },
        {
          "id": "stocks",
          "label": "Stocks",
          "column": 6,
          "unit": "metric tons (t) cadmium content",
          "price_basis": "not-price",
          "observation_count": 53,
          "year_start": 1940,
          "year_end": 1992,
          "missing": {
            "blank": 0,
            "not_available": 40,
            "withheld": 0,
            "other_nonnumeric": 0
          },
          "observations": [
            [
              1940,
              1290,
              46
            ],
            [
              1941,
              1180,
              47
            ],
            [
              1942,
              914,
              48
            ],
            [
              1943,
              1450,
              49
            ],
            [
              1944,
              1270,
              50
            ],
            [
              1945,
              706,
              51
            ],
            [
              1946,
              457,
              52
            ],
            [
              1947,
              578,
              53
            ],
            [
              1948,
              213,
              54
            ],
            [
              1949,
              316,
              55
            ],
            [
              1950,
              266,
              56
            ],
            [
              1951,
              509,
              57
            ],
            [
              1952,
              847,
              58
            ],
            [
              1953,
              1530,
              59
            ],
            [
              1954,
              2190,
              60
            ],
            [
              1955,
              1650,
              61
            ],
            [
              1956,
              1520,
              62
            ],
            [
              1957,
              1670,
              63
            ],
            [
              1958,
              2540,
              64
            ],
            [
              1959,
              1570,
              65
            ],
            [
              1960,
              894,
              66
            ],
            [
              1961,
              1040,
              67
            ],
            [
              1962,
              570,
              68
            ],
            [
              1963,
              626,
              69
            ],
            [
              1964,
              980,
              70
            ],
            [
              1965,
              1560,
              71
            ],
            [
              1966,
              1130,
              72
            ],
            [
              1967,
              699,
              73
            ],
            [
              1968,
              499,
              74
            ],
            [
              1969,
              650,
              75
            ],
            [
              1970,
              1740,
              76
            ],
            [
              1971,
              1950,
              77
            ],
            [
              1972,
              1060,
              78
            ],
            [
              1973,
              694,
              79
            ],
            [
              1974,
              906,
              80
            ],
            [
              1975,
              2200,
              81
            ],
            [
              1976,
              1640,
              82
            ],
            [
              1977,
              1780,
              83
            ],
            [
              1978,
              1490,
              84
            ],
            [
              1979,
              896,
              85
            ],
            [
              1980,
              1320,
              86
            ],
            [
              1981,
              1360,
              87
            ],
            [
              1982,
              952,
              88
            ],
            [
              1983,
              349,
              89
            ],
            [
              1984,
              351,
              90
            ],
            [
              1985,
              306,
              91
            ],
            [
              1986,
              441,
              92
            ],
            [
              1987,
              261,
              93
            ],
            [
              1988,
              481,
              94
            ],
            [
              1989,
              326,
              95
            ],
            [
              1990,
              336,
              96
            ],
            [
              1991,
              725,
              97
            ],
            [
              1992,
              588,
              98
            ]
          ]
        },
        {
          "id": "apparent-consumption",
          "label": "Apparent consumption",
          "column": 7,
          "unit": "metric tons (t) cadmium content",
          "price_basis": "not-price",
          "observation_count": 90,
          "year_start": 1903,
          "year_end": 1992,
          "missing": {
            "blank": 0,
            "not_available": 3,
            "withheld": 0,
            "other_nonnumeric": 0
          },
          "observations": [
            [
              1903,
              3.94,
              9
            ],
            [
              1904,
              3.47,
              10
            ],
            [
              1905,
              3.69,
              11
            ],
            [
              1906,
              6.4,
              12
            ],
            [
              1907,
              7.24,
              13
            ],
            [
              1908,
              5.25,
              14
            ],
            [
              1909,
              6.43,
              15
            ],
            [
              1910,
              3.97,
              16
            ],
            [
              1911,
              14.3,
              17
            ],
            [
              1912,
              8.2,
              18
            ],
            [
              1913,
              25.3,
              19
            ],
            [
              1914,
              39.8,
              20
            ],
            [
              1915,
              41.6,
              21
            ],
            [
              1916,
              43.6,
              22
            ],
            [
              1917,
              94.1,
              23
            ],
            [
              1918,
              38.5,
              24
            ],
            [
              1919,
              45.3,
              25
            ],
            [
              1920,
              45.3,
              26
            ],
            [
              1921,
              31.1,
              27
            ],
            [
              1922,
              60.7,
              28
            ],
            [
              1923,
              83.4,
              29
            ],
            [
              1924,
              59.2,
              30
            ],
            [
              1925,
              228,
              31
            ],
            [
              1926,
              368,
              32
            ],
            [
              1927,
              497,
              33
            ],
            [
              1928,
              957,
              34
            ],
            [
              1929,
              1420,
              35
            ],
            [
              1930,
              1420,
              36
            ],
            [
              1931,
              630,
              37
            ],
            [
              1932,
              480,
              38
            ],
            [
              1933,
              1260,
              39
            ],
            [
              1934,
              1570,
              40
            ],
            [
              1935,
              1890,
              41
            ],
            [
              1936,
              2190,
              42
            ],
            [
              1937,
              2690,
              43
            ],
            [
              1938,
              1850,
              44
            ],
            [
              1939,
              2680,
              45
            ],
            [
              1940,
              2800,
              46
            ],
            [
              1941,
              3520,
              47
            ],
            [
              1942,
              3470,
              48
            ],
            [
              1943,
              3350,
              49
            ],
            [
              1944,
              4020,
              50
            ],
            [
              1945,
              3920,
              51
            ],
            [
              1946,
              3170,
              52
            ],
            [
              1947,
              3510,
              53
            ],
            [
              1948,
              3540,
              54
            ],
            [
              1949,
              3400,
              55
            ],
            [
              1950,
              4330,
              56
            ],
            [
              1951,
              3250,
              57
            ],
            [
              1952,
              4090,
              58
            ],
            [
              1953,
              4340,
              59
            ],
            [
              1954,
              3400,
              60
            ],
            [
              1955,
              4850,
              61
            ],
            [
              1956,
              5770,
              62
            ],
            [
              1957,
              4990,
              63
            ],
            [
              1958,
              3720,
              64
            ],
            [
              1959,
              5180,
              65
            ],
            [
              1960,
              4590,
              66
            ],
            [
              1961,
              4620,
              67
            ],
            [
              1962,
              5510,
              68
            ],
            [
              1963,
              5210,
              69
            ],
            [
              1964,
              4250,
              70
            ],
            [
              1965,
              4730,
              71
            ],
            [
              1966,
              6700,
              72
            ],
            [
              1967,
              5250,
              73
            ],
            [
              1968,
              6050,
              74
            ],
            [
              1969,
              6830,
              75
            ],
            [
              1970,
              4110,
              76
            ],
            [
              1971,
              4930,
              77
            ],
            [
              1972,
              5720,
              78
            ],
            [
              1973,
              5690,
              79
            ],
            [
              1974,
              5490,
              80
            ],
            [
              1975,
              3060,
              81
            ],
            [
              1976,
              5380,
              82
            ],
            [
              1977,
              3820,
              83
            ],
            [
              1978,
              4510,
              84
            ],
            [
              1979,
              4930,
              85
            ],
            [
              1980,
              3530,
              86
            ],
            [
              1981,
              4380,
              87
            ],
            [
              1982,
              3730,
              88
            ],
            [
              1983,
              3760,
              89
            ],
            [
              1984,
              3300,
              90
            ],
            [
              1985,
              3720,
              91
            ],
            [
              1986,
              4390,
              92
            ],
            [
              1987,
              4180,
              93
            ],
            [
              1988,
              3620,
              94
            ],
            [
              1989,
              4100,
              95
            ],
            [
              1990,
              3110,
              96
            ],
            [
              1991,
              3080,
              97
            ],
            [
              1992,
              3270,
              98
            ]
          ]
        },
        {
          "id": "unit-value-t",
          "label": "Unit value ($/t)",
          "column": 8,
          "unit": "current U.S. dollars per metric ton",
          "price_basis": "nominal",
          "observation_count": 93,
          "year_start": 1900,
          "year_end": 1992,
          "missing": {
            "blank": 0,
            "not_available": 0,
            "withheld": 0,
            "other_nonnumeric": 0
          },
          "observations": [
            [
              1900,
              1430,
              6
            ],
            [
              1901,
              1500,
              7
            ],
            [
              1902,
              1190,
              8
            ],
            [
              1903,
              1170,
              9
            ],
            [
              1904,
              1300,
              10
            ],
            [
              1905,
              1430,
              11
            ],
            [
              1906,
              1680,
              12
            ],
            [
              1907,
              1850,
              13
            ],
            [
              1908,
              1650,
              14
            ],
            [
              1909,
              1150,
              15
            ],
            [
              1910,
              1210,
              16
            ],
            [
              1911,
              1480,
              17
            ],
            [
              1912,
              1680,
              18
            ],
            [
              1913,
              1700,
              19
            ],
            [
              1914,
              1960,
              20
            ],
            [
              1915,
              2620,
              21
            ],
            [
              1916,
              3440,
              22
            ],
            [
              1917,
              3240,
              23
            ],
            [
              1918,
              3260,
              24
            ],
            [
              1919,
              2690,
              25
            ],
            [
              1920,
              2580,
              26
            ],
            [
              1921,
              2160,
              27
            ],
            [
              1922,
              2400,
              28
            ],
            [
              1923,
              1940,
              29
            ],
            [
              1924,
              1320,
              30
            ],
            [
              1925,
              1320,
              31
            ],
            [
              1926,
              1320,
              32
            ],
            [
              1927,
              1320,
              33
            ],
            [
              1928,
              1320,
              34
            ],
            [
              1929,
              1320,
              35
            ],
            [
              1930,
              1320,
              36
            ],
            [
              1931,
              1210,
              37
            ],
            [
              1932,
              1210,
              38
            ],
            [
              1933,
              1210,
              39
            ],
            [
              1934,
              1210,
              40
            ],
            [
              1935,
              1540,
              41
            ],
            [
              1936,
              2160,
              42
            ],
            [
              1937,
              2690,
              43
            ],
            [
              1938,
              2160,
              44
            ],
            [
              1939,
              1410,
              45
            ],
            [
              1940,
              1810,
              46
            ],
            [
              1941,
              1980,
              47
            ],
            [
              1942,
              1740,
              48
            ],
            [
              1943,
              1740,
              49
            ],
            [
              1944,
              1650,
              50
            ],
            [
              1945,
              1700,
              51
            ],
            [
              1946,
              2180,
              52
            ],
            [
              1947,
              3460,
              53
            ],
            [
              1948,
              3660,
              54
            ],
            [
              1949,
              4410,
              55
            ],
            [
              1950,
              4780,
              56
            ],
            [
              1951,
              5620,
              57
            ],
            [
              1952,
              4920,
              58
            ],
            [
              1953,
              4410,
              59
            ],
            [
              1954,
              3750,
              60
            ],
            [
              1955,
              3750,
              61
            ],
            [
              1956,
              3750,
              62
            ],
            [
              1957,
              3750,
              63
            ],
            [
              1958,
              3350,
              64
            ],
            [
              1959,
              2980,
              65
            ],
            [
              1960,
              3350,
              66
            ],
            [
              1961,
              3700,
              67
            ],
            [
              1962,
              3790,
              68
            ],
            [
              1963,
              4980,
              69
            ],
            [
              1964,
              6610,
              70
            ],
            [
              1965,
              5690,
              71
            ],
            [
              1966,
              5340,
              72
            ],
            [
              1967,
              5820,
              73
            ],
            [
              1968,
              5840,
              74
            ],
            [
              1969,
              7210,
              75
            ],
            [
              1970,
              7870,
              76
            ],
            [
              1971,
              4230,
              77
            ],
            [
              1972,
              5640,
              78
            ],
            [
              1973,
              8020,
              79
            ],
            [
              1974,
              9020,
              80
            ],
            [
              1975,
              7410,
              81
            ],
            [
              1976,
              5860,
              82
            ],
            [
              1977,
              6530,
              83
            ],
            [
              1978,
              5400,
              84
            ],
            [
              1979,
              6080,
              85
            ],
            [
              1980,
              6260,
              86
            ],
            [
              1981,
              4250,
              87
            ],
            [
              1982,
              2450,
              88
            ],
            [
              1983,
              2490,
              89
            ],
            [
              1984,
              3730,
              90
            ],
            [
              1985,
              2670,
              91
            ],
            [
              1986,
              2760,
              92
            ],
            [
              1987,
              4380,
              93
            ],
            [
              1988,
              15200,
              94
            ],
            [
              1989,
              13800,
              95
            ],
            [
              1990,
              7450,
              96
            ],
            [
              1991,
              4430,
              97
            ],
            [
              1992,
              2000,
              98
            ]
          ]
        },
        {
          "id": "unit-value-98-t",
          "label": "Unit value (98 $/t)",
          "column": 9,
          "unit": "1998 U.S. dollars per metric ton",
          "price_basis": "real-1998-dollars",
          "observation_count": 93,
          "year_start": 1900,
          "year_end": 1992,
          "missing": {
            "blank": 0,
            "not_available": 0,
            "withheld": 0,
            "other_nonnumeric": 0
          },
          "observations": [
            [
              1900,
              28000,
              6
            ],
            [
              1901,
              29000,
              7
            ],
            [
              1902,
              22000,
              8
            ],
            [
              1903,
              21000,
              9
            ],
            [
              1904,
              24000,
              10
            ],
            [
              1905,
              26000,
              11
            ],
            [
              1906,
              31000,
              12
            ],
            [
              1907,
              32000,
              13
            ],
            [
              1908,
              30000,
              14
            ],
            [
              1909,
              21000,
              15
            ],
            [
              1910,
              21000,
              16
            ],
            [
              1911,
              26000,
              17
            ],
            [
              1912,
              28000,
              18
            ],
            [
              1913,
              28000,
              19
            ],
            [
              1914,
              32000,
              20
            ],
            [
              1915,
              42300,
              21
            ],
            [
              1916,
              51400,
              22
            ],
            [
              1917,
              41300,
              23
            ],
            [
              1918,
              35200,
              24
            ],
            [
              1919,
              25400,
              25
            ],
            [
              1920,
              21000,
              26
            ],
            [
              1921,
              19700,
              27
            ],
            [
              1922,
              23300,
              28
            ],
            [
              1923,
              18500,
              29
            ],
            [
              1924,
              12600,
              30
            ],
            [
              1925,
              12300,
              31
            ],
            [
              1926,
              12200,
              32
            ],
            [
              1927,
              12400,
              33
            ],
            [
              1928,
              12600,
              34
            ],
            [
              1929,
              12600,
              35
            ],
            [
              1930,
              12900,
              36
            ],
            [
              1931,
              13000,
              37
            ],
            [
              1932,
              14400,
              38
            ],
            [
              1933,
              15200,
              39
            ],
            [
              1934,
              14700,
              40
            ],
            [
              1935,
              18300,
              41
            ],
            [
              1936,
              25300,
              42
            ],
            [
              1937,
              30500,
              43
            ],
            [
              1938,
              25000,
              44
            ],
            [
              1939,
              16500,
              45
            ],
            [
              1940,
              21100,
              46
            ],
            [
              1941,
              22000,
              47
            ],
            [
              1942,
              17400,
              48
            ],
            [
              1943,
              16400,
              49
            ],
            [
              1944,
              15300,
              50
            ],
            [
              1945,
              15400,
              51
            ],
            [
              1946,
              18200,
              52
            ],
            [
              1947,
              25300,
              53
            ],
            [
              1948,
              24700,
              54
            ],
            [
              1949,
              30200,
              55
            ],
            [
              1950,
              32300,
              56
            ],
            [
              1951,
              35200,
              57
            ],
            [
              1952,
              30300,
              58
            ],
            [
              1953,
              26900,
              59
            ],
            [
              1954,
              22700,
              60
            ],
            [
              1955,
              22800,
              61
            ],
            [
              1956,
              22500,
              62
            ],
            [
              1957,
              21800,
              63
            ],
            [
              1958,
              18900,
              64
            ],
            [
              1959,
              16700,
              65
            ],
            [
              1960,
              18400,
              66
            ],
            [
              1961,
              20200,
              67
            ],
            [
              1962,
              20500,
              68
            ],
            [
              1963,
              26500,
              69
            ],
            [
              1964,
              34800,
              70
            ],
            [
              1965,
              29400,
              71
            ],
            [
              1966,
              26900,
              72
            ],
            [
              1967,
              28400,
              73
            ],
            [
              1968,
              27400,
              74
            ],
            [
              1969,
              32000,
              75
            ],
            [
              1970,
              33100,
              76
            ],
            [
              1971,
              17000,
              77
            ],
            [
              1972,
              22000,
              78
            ],
            [
              1973,
              29400,
              79
            ],
            [
              1974,
              29800,
              80
            ],
            [
              1975,
              22400,
              81
            ],
            [
              1976,
              16800,
              82
            ],
            [
              1977,
              17600,
              83
            ],
            [
              1978,
              13500,
              84
            ],
            [
              1979,
              13700,
              85
            ],
            [
              1980,
              12400,
              86
            ],
            [
              1981,
              7620,
              87
            ],
            [
              1982,
              4140,
              88
            ],
            [
              1983,
              4080,
              89
            ],
            [
              1984,
              5850,
              90
            ],
            [
              1985,
              4040,
              91
            ],
            [
              1986,
              4100,
              92
            ],
            [
              1987,
              6280,
              93
            ],
            [
              1988,
              20900,
              94
            ],
            [
              1989,
              18100,
              95
            ],
            [
              1990,
              9290,
              96
            ],
            [
              1991,
              5300,
              97
            ],
            [
              1992,
              2320,
              98
            ]
          ]
        },
        {
          "id": "world-production",
          "label": "World production",
          "column": 10,
          "unit": "metric tons (t) cadmium content",
          "price_basis": "not-price",
          "observation_count": 93,
          "year_start": 1900,
          "year_end": 1992,
          "missing": {
            "blank": 0,
            "not_available": 0,
            "withheld": 0,
            "other_nonnumeric": 0
          },
          "observations": [
            [
              1900,
              14,
              6
            ],
            [
              1901,
              13,
              7
            ],
            [
              1902,
              13,
              8
            ],
            [
              1903,
              17,
              9
            ],
            [
              1904,
              25,
              10
            ],
            [
              1905,
              25,
              11
            ],
            [
              1906,
              21,
              12
            ],
            [
              1907,
              39,
              13
            ],
            [
              1908,
              37,
              14
            ],
            [
              1909,
              39,
              15
            ],
            [
              1910,
              43,
              16
            ],
            [
              1911,
              55,
              17
            ],
            [
              1912,
              67,
              18
            ],
            [
              1913,
              62,
              19
            ],
            [
              1914,
              80,
              20
            ],
            [
              1915,
              78,
              21
            ],
            [
              1916,
              119,
              22
            ],
            [
              1917,
              172,
              23
            ],
            [
              1918,
              165,
              24
            ],
            [
              1919,
              89,
              25
            ],
            [
              1920,
              81,
              26
            ],
            [
              1921,
              54,
              27
            ],
            [
              1922,
              128,
              28
            ],
            [
              1923,
              248,
              29
            ],
            [
              1924,
              245,
              30
            ],
            [
              1925,
              416,
              31
            ],
            [
              1926,
              960,
              32
            ],
            [
              1927,
              661,
              33
            ],
            [
              1928,
              1500,
              34
            ],
            [
              1929,
              2180,
              35
            ],
            [
              1930,
              2480,
              36
            ],
            [
              1931,
              1230,
              37
            ],
            [
              1932,
              1040,
              38
            ],
            [
              1933,
              1950,
              39
            ],
            [
              1934,
              2480,
              40
            ],
            [
              1935,
              3150,
              41
            ],
            [
              1936,
              3390,
              42
            ],
            [
              1937,
              3970,
              43
            ],
            [
              1938,
              4010,
              44
            ],
            [
              1939,
              4580,
              45
            ],
            [
              1940,
              5220,
              46
            ],
            [
              1941,
              5220,
              47
            ],
            [
              1942,
              5030,
              48
            ],
            [
              1943,
              5380,
              49
            ],
            [
              1944,
              5320,
              50
            ],
            [
              1945,
              4760,
              51
            ],
            [
              1946,
              4050,
              52
            ],
            [
              1947,
              4930,
              53
            ],
            [
              1948,
              4870,
              54
            ],
            [
              1949,
              5220,
              55
            ],
            [
              1950,
              6010,
              56
            ],
            [
              1951,
              6070,
              57
            ],
            [
              1952,
              6170,
              58
            ],
            [
              1953,
              7060,
              59
            ],
            [
              1954,
              7300,
              60
            ],
            [
              1955,
              8390,
              61
            ],
            [
              1956,
              9070,
              62
            ],
            [
              1957,
              9390,
              63
            ],
            [
              1958,
              9800,
              64
            ],
            [
              1959,
              10200,
              65
            ],
            [
              1960,
              11100,
              66
            ],
            [
              1961,
              11700,
              67
            ],
            [
              1962,
              11700,
              68
            ],
            [
              1963,
              11800,
              69
            ],
            [
              1964,
              12700,
              70
            ],
            [
              1965,
              11900,
              71
            ],
            [
              1966,
              13000,
              72
            ],
            [
              1967,
              13200,
              73
            ],
            [
              1968,
              15000,
              74
            ],
            [
              1969,
              17600,
              75
            ],
            [
              1970,
              16500,
              76
            ],
            [
              1971,
              15400,
              77
            ],
            [
              1972,
              16700,
              78
            ],
            [
              1973,
              17200,
              79
            ],
            [
              1974,
              17300,
              80
            ],
            [
              1975,
              15200,
              81
            ],
            [
              1976,
              17000,
              82
            ],
            [
              1977,
              18300,
              83
            ],
            [
              1978,
              17300,
              84
            ],
            [
              1979,
              18700,
              85
            ],
            [
              1980,
              18200,
              86
            ],
            [
              1981,
              17400,
              87
            ],
            [
              1982,
              16400,
              88
            ],
            [
              1983,
              17600,
              89
            ],
            [
              1984,
              19600,
              90
            ],
            [
              1985,
              19100,
              91
            ],
            [
              1986,
              19100,
              92
            ],
            [
              1987,
              19000,
              93
            ],
            [
              1988,
              21900,
              94
            ],
            [
              1989,
              21400,
              95
            ],
            [
              1990,
              20200,
              96
            ],
            [
              1991,
              20900,
              97
            ],
            [
              1992,
              19600,
              98
            ]
          ]
        }
      ]
    }
  ]
}
